zalosdk/__init__.py
zalosdk/client.py
zalosdk/endpoint.py
zalosdk/error_code.py
zalosdk/message.py
zalosdk/template.py
zalopysdk-0.1.1.dist-info/METADATA
zalopysdk-0.1.1.dist-info/WHEEL
zalopysdk-0.1.1.dist-info/top_level.txt
zalopysdk-0.1.1.dist-info/RECORD
