Metadata-Version: 2.1
Name: zalopysdk
Version: 0.1.1
Summary: A Python SDK for Zalo API integration
Home-page: https://github.com/ducminhgd/zalo-python-sdk
Author: Giã Dương Đức Minh
Author-email: giaduongducminh@gmail.com
Classifier: Development Status :: 3 - Alpha
Classifier: Intended Audience :: Developers
Classifier: License :: OSI Approved :: MIT License
Classifier: Operating System :: OS Independent
Classifier: Programming Language :: Python :: 3
Classifier: Programming Language :: Python :: 3.6
Classifier: Programming Language :: Python :: 3.7
Classifier: Programming Language :: Python :: 3.8
Classifier: Programming Language :: Python :: 3.9
Classifier: Programming Language :: Python :: 3.10
Classifier: Programming Language :: Python :: 3.11
Classifier: Programming Language :: Python :: 3.12
Requires-Python: >=3.6
Requires-Dist: pkce==1.0.3
Requires-Dist: requests==2.32.3
